{
  "with_afd": [
    {
      "parties": [
        "CDU/CSU",
        "AfD"
      ],
      "total": 50.8,
      "possible": true
    },
    {
      "parties": [
        "CDU/CSU",
        "AfD",
        "Sonstige"
      ],
      "total": 56.0,
      "possible": true
    }
  ],
  "without_afd": [
    {
      "parties": [
        "CDU/CSU",
        "SPD",
        "GRÜNE"
      ],
      "total": 58.9,
      "possible": true
    },
    {
      "parties": [
        "CDU/CSU",
        "SPD",
        "DIE LINKE"
      ],
      "total": 51.8,
      "possible": true
    },
    {
      "parties": [
        "CDU/CSU",
        "SPD",
        "Sonstige"
      ],
      "total": 50.7,
      "possible": true
    },
    {
      "parties": [
        "CDU/CSU",
        "GRÜNE",
        "DIE LINKE"
      ],
      "total": 50.1,
      "possible": true
    }
  ],
  "minority_with_afd": []
}